cygnet_common-0.1.0.dist-info/METADATA
cygnet_common-0.1.0.dist-info/WHEEL
cygnet_common-0.1.0.dist-info/metadata.json
cygnet_common-0.1.0.dist-info/RECORD
cygnet_common-0.1.0.dist-info/top_level.txt
cygnet_common-0.1.0.dist-info/DESCRIPTION.rst
cygnet_common/__main__.py
cygnet_common/interfaces.py
cygnet_common/__init__.py
cygnet_common/NetworkInterface.py
cygnet_common/strtypes.py
cygnet_common/Structures.py
cygnet_common/MutantDict.py
cygnet_common/design/__init__.py
cygnet_common/design/Task.py
cygnet_common/jsonrpc/trans-req
cygnet_common/jsonrpc/OVSExceptions.py
cygnet_common/jsonrpc/__init__.py
cygnet_common/jsonrpc/test.py
cygnet_common/jsonrpc/s
cygnet_common/jsonrpc/OpenvSwitchClient.py
cygnet_common/jsonrpc/OpenvSwitchTables.py
cygnet_common/jsonrpc/meta.py
cygnet_common/jsonrpc/TODO
cygnet_common/jsonrpc/OpenvSwitchState.py
cygnet_common/jsonrpc/OVSTypes.py
cygnet_common/jsonrpc/mon-response
cygnet_common/jsonrpc/operations/__init__.py
cygnet_common/jsonrpc/operations/Transaction.py
cygnet_common/jsonrpc/helpers/__init__.py
cygnet_common/jsonrpc/helpers/Switch.py
cygnet_common/jsonrpc/helpers/Interface.py
cygnet_common/jsonrpc/helpers/Port.py
cygnet_common/jsonrpc/helpers/Bridge.py
cygnet_common/jsonrpc/Meta/__init__.py
cygnet_common/jsonrpc/Meta/Patterns.py
cygnet_common/Meta/__init__.py
cygnet_common/Meta/Patterns.py
